testspeednet/__init__.py
testspeednet/py.typed
testspeednet/conf/apis.yaml
testspeednet/conf/testspeednet.cfg
testspeednet/conf/testspeednet.logo
testspeednet/conf/testspeednet_util.cfg
testspeednet/log/testspeednet.log
testspeednet/net/__init__.py
testspeednet/net/config.py
testspeednet/net/download.py
testspeednet/net/model.py
testspeednet/net/speed.py
testspeednet/net/test.py
testspeednet/net/upload.py
testspeednet/net/utils/__init__.py
testspeednet/net/utils/catch_request.py
testspeednet/net/utils/checking_servers.py
testspeednet/net/utils/connector.py
testspeednet/net/utils/distance.py
testspeednet/net/utils/do_nothing.py
testspeednet/net/utils/fake_shutdown_event.py
testspeednet/net/utils/get_exception.py
testspeednet/net/utils/get_response_stream.py
testspeednet/net/utils/gzip_decoded_response.py
testspeednet/net/utils/http_downloader.py
testspeednet/net/utils/http_uploader.py
testspeednet/net/utils/http_uploader_data.py
testspeednet/net/utils/net_exceptions.py
testspeednet/net/utils/opener.py
testspeednet/net/utils/printer.py
testspeednet/net/utils/requester.py
testspeednet/net/utils/test_http_connection.py
testspeednet/net/utils/test_http_handler.py
testspeednet/net/utils/test_https_connection.py
testspeednet/net/utils/test_https_handler.py
testspeednet/net/utils/test_net_config.py
testspeednet/net/utils/test_results.py
testspeednet/net/utils/user_agent.py
usr/local/bin/testspeednet_run.py
testspeednet-1.0.2.dist-info/LICENSE
testspeednet-1.0.2.dist-info/METADATA
testspeednet-1.0.2.dist-info/WHEEL
testspeednet-1.0.2.dist-info/top_level.txt
testspeednet-1.0.2.dist-info/RECORD
